CHANGES.txt
MANIFEST.in
README.rst
setup.py
isotoma/__init__.py
isotoma.recipe.gocaptain.egg-info/PKG-INFO
isotoma.recipe.gocaptain.egg-info/SOURCES.txt
isotoma.recipe.gocaptain.egg-info/dependency_links.txt
isotoma.recipe.gocaptain.egg-info/entry_points.txt
isotoma.recipe.gocaptain.egg-info/namespace_packages.txt
isotoma.recipe.gocaptain.egg-info/not-zip-safe
isotoma.recipe.gocaptain.egg-info/requires.txt
isotoma.recipe.gocaptain.egg-info/top_level.txt
isotoma/recipe/__init__.py
isotoma/recipe/gocaptain/__init__.py
isotoma/recipe/gocaptain/lsb.tmpl
isotoma/recipe/gocaptain/simple.tmpl
isotoma/recipe/gocaptain/test/__init__.py
isotoma/recipe/gocaptain/test/basic.tmpl
isotoma/recipe/gocaptain/test/test_gocaptain.py