Metadata-Version: 1.0
Name: isotoma.recipe.gocaptain
Version: 0.0.9
Summary: Starting and stopping daemons
Home-page: http://pypi.python.org/pypi/isotoma.recipe.gocaptain
Author: Doug Winter
Author-email: doug.winter@isotoma.com
License: Apache Software License
Keywords: buildout
Platform: UNKNOWN
Classifier: Framework :: Buildout
Classifier: Intended Audience :: System Administrators
Classifier: Operating System :: POSIX
Classifier: License :: OSI Approved :: Apache Software License
